{
  "version": "1",
  "cognitoConfig": {
    "identityPoolName": "nbustudiod032f512_identitypool_d032f512",
    "allowUnauthenticatedIdentities": false,
    "resourceNameTruncated": "nbustud032f512",
    "userPoolName": "nbustudiod032f512_userpool_d032f512",
    "autoVerifiedAttributes": ["email"],
    "mfaConfiguration": "OFF",
    "mfaTypes": ["SMS Text Message"],
    "smsAuthenticationMessage": "Your authentication code is {####}",
    "smsVerificationMessage": "Your verification code is {####}",
    "emailVerificationSubject": "Your verification code",
    "emailVerificationMessage": "Your verification code is {####}",
    "defaultPasswordPolicy": false,
    "passwordPolicyMinLength": 8,
    "passwordPolicyCharacters": [],
    "requiredAttributes": ["email"],
    "aliasAttributes": [],
    "userpoolClientGenerateSecret": false,
    "userpoolClientRefreshTokenValidity": 30,
    "userpoolClientWriteAttributes": ["email"],
    "userpoolClientReadAttributes": ["email"],
    "userpoolClientLambdaRole": "nbustud032f512_userpoolclient_lambda_role",
    "userpoolClientSetAttributes": false,
    "sharedId": "d032f512",
    "resourceName": "nbustudiod032f512",
    "authSelections": "identityPoolAndUserPool",
    "useDefault": "default",
    "usernameAttributes": ["email"],
    "userPoolGroupList": [],
    "serviceName": "Cognito",
    "usernameCaseSensitive": false,
    "useEnabledMfas": true
  }
}
